nestedtext/__init__.py
nestedtext/__init__.pyi
nestedtext/nestedtext.py
nestedtext/nestedtext.pyi
nestedtext/py.typed
nestedtext-3.8.dist-info/licenses/LICENSE
nestedtext-3.8.dist-info/WHEEL
nestedtext-3.8.dist-info/METADATA
nestedtext-3.8.dist-info/RECORD
