Metadata-Version: 2.4
Name: nestedtext
Version: 3.8
Summary: human readable and writable data interchange format
Keywords: data,serialization,json,yaml
Author: Ken Kundert, Kale Kundert
Author-email: nestedtext@nurdletech.com
Requires-Python: >=3.6
Classifier: Development Status :: 5 - Production/Stable
Classifier: Intended Audience :: Developers
Classifier: License :: OSI Approved :: MIT License
Classifier: Natural Language :: English
Classifier: Operating System :: POSIX :: Linux
Classifier: Programming Language :: Python :: 3
Classifier: Topic :: Text Processing :: Markup
Classifier: Topic :: Utilities
License-File: LICENSE
Requires-Dist: inform>=1.28
Project-URL: changelog, https://github.com/KenKundert/nestedtext/blob/master/doc/releases.rst
Project-URL: documentation, https://nestedtext.org
Project-URL: homepage, https://nestedtext.org
Project-URL: repository, https://github.com/kenkundert/nestedtext
